br_helper/br_helper.py
br_helper-0.1.4.dist-info/LICENSE
br_helper-0.1.4.dist-info/METADATA
br_helper-0.1.4.dist-info/WHEEL
br_helper-0.1.4.dist-info/top_level.txt
br_helper-0.1.4.dist-info/RECORD
