Metadata-Version: 2.1
Name: br-helper
Version: 0.1.4
Summary: Automate browser the easy way
Home-page: https://github.com/Tornike-Skhulukhia/browser_automation_helper
Author: Tornike Skhulukhia
Author-email: Tornike.Skhulukhia.1@iliauni.edu.ge
License: MIT
Platform: UNKNOWN
Classifier: Programming Language :: Python :: 3
Classifier: License :: OSI Approved :: MIT License
Classifier: Operating System :: OS Independent
Requires-Python: >=3.6
Requires-Dist: selenium (>=3.141.0)
Requires-Dist: beautifulsoup4 (>=4.6.0)
